{ "skeleton": { "images": "/d/OneDrive - DoreAzure/Outside/ThaiAnh/Final Character/Image/back_hand/" },
"bones": [
	{ "name": "root" }
],
"slots": [
	{ "name": "M_Human_back_hand", "bone": "root", "attachment": "M_Human_back_hand" },
	{ "name": "M_Elf_back_hand", "bone": "root", "attachment": "M_Elf_back_hand" },
	{ "name": "M_Devil_back_hand", "bone": "root", "attachment": "M_Devil_back_hand" },
	{ "name": "M_Orc_back_hand", "bone": "root", "attachment": "M_Orc_back_hand" },
	{ "name": "M_Steamborg_back_hand", "bone": "root", "attachment": "M_Steamborg_back_hand" },
	{ "name": "M_Undead_back_hand", "bone": "root", "attachment": "M_Undead_back_hand" },
	{ "name": "M_Angel_back_hand", "bone": "root", "attachment": "M_Angel_back_hand" },
	{ "name": "FM_Human_back_hand", "bone": "root", "attachment": "FM_Human_back_hand" },
	{ "name": "FM_Elf_back_hand", "bone": "root", "attachment": "FM_Elf_back_hand" },
	{ "name": "FM_Devil_back_hand", "bone": "root", "attachment": "FM_Devil_back_hand" },
	{ "name": "FM_Orc_back_hand", "bone": "root", "attachment": "FM_Orc_back_hand" },
	{ "name": "FM_Steamborg_back_hand", "bone": "root", "attachment": "FM_Steamborg_back_hand" },
	{ "name": "FM_Undead_back_hand", "bone": "root", "attachment": "FM_Undead_back_hand" },
	{ "name": "FM_Angle_back_hand", "bone": "root", "attachment": "FM_Angle_back_hand" }
],
"skins": {
	"default": {
		"M_Human_back_hand": {
			"M_Human_back_hand": { "x": 56.5, "y": -56.5, "width": 115, "height": 115 }
		},
		"M_Elf_back_hand": {
			"M_Elf_back_hand": { "x": 56.5, "y": -56.5, "width": 115, "height": 115 }
		},
		"M_Devil_back_hand": {
			"M_Devil_back_hand": { "x": 56.5, "y": -56.5, "width": 115, "height": 115 }
		},
		"M_Orc_back_hand": {
			"M_Orc_back_hand": { "x": 56.5, "y": -56.5, "width": 115, "height": 115 }
		},
		"M_Steamborg_back_hand": {
			"M_Steamborg_back_hand": { "x": 56.5, "y": -56.5, "width": 115, "height": 115 }
		},
		"M_Undead_back_hand": {
			"M_Undead_back_hand": { "x": 56.5, "y": -56.5, "width": 115, "height": 115 }
		},
		"M_Angel_back_hand": {
			"M_Angel_back_hand": { "x": 56.5, "y": -56.5, "width": 115, "height": 115 }
		},
		"FM_Human_back_hand": {
			"FM_Human_back_hand": { "x": 56.5, "y": -56.5, "width": 115, "height": 115 }
		},
		"FM_Elf_back_hand": {
			"FM_Elf_back_hand": { "x": 56.5, "y": -56.5, "width": 115, "height": 115 }
		},
		"FM_Devil_back_hand": {
			"FM_Devil_back_hand": { "x": 56.5, "y": -56.5, "width": 115, "height": 115 }
		},
		"FM_Orc_back_hand": {
			"FM_Orc_back_hand": { "x": 56.5, "y": -56.5, "width": 115, "height": 115 }
		},
		"FM_Steamborg_back_hand": {
			"FM_Steamborg_back_hand": { "x": 56.5, "y": -56.5, "width": 115, "height": 115 }
		},
		"FM_Undead_back_hand": {
			"FM_Undead_back_hand": { "x": 56.5, "y": -56.5, "width": 115, "height": 115 }
		},
		"FM_Angle_back_hand": {
			"FM_Angle_back_hand": { "x": 56.5, "y": -56.5, "width": 115, "height": 115 }
		}
	}
},
"animations": { "animation": {} }
}